intelligenzaartificiale/__init__.py
intelligenzaartificiale/bigdataset.py
intelligenzaartificiale/dataset.py
intelligenzaartificiale/machinelearning.py
intelligenzaartificiale/preprocessing.py
intelligenzaartificiale/statistica.py
intelligenzaartificiale/textpreprocessing.py
intelligenzaartificiale/visualizzazione.py
intelligenzaartificiale-0.0.0.38.dist-info/LICENSE
intelligenzaartificiale-0.0.0.38.dist-info/METADATA
intelligenzaartificiale-0.0.0.38.dist-info/WHEEL
intelligenzaartificiale-0.0.0.38.dist-info/top_level.txt
intelligenzaartificiale-0.0.0.38.dist-info/RECORD
