Metadata-Version: 2.1
Name: intelligenzaartificiale
Version: 0.0.0.38
Summary: Intelligenza Artificiale la libreria python italiana dedicata all'I.A.
Home-page: https://github.com/IntelligenzaArtificilaeItalia/IntelligenzaArtificiale
Author: intelligenzaartificialeitalia.net
Author-email: ceo@intelligenzaartificialeitalia.net
License: UNKNOWN
Project-URL: Bug Tracker, https://github.com/IntelligenzaArtificilaeItalia/IntelligenzaArtificiale/issues
Project-URL: Documentation, https://pypi.org/project/intelligenzaartificiale/
Project-URL: Examples, https://github.com/IntelligenzaArtificilaeItalia/IntelligenzaArtificiale/tree/main/Esempi%20di%20pratico%20Utilizzo
Project-URL: Website, https://intelligenzaartificialeitalia.net/
Platform: UNKNOWN
Classifier: Programming Language :: Python :: 3
Classifier: License :: OSI Approved :: MIT License
Classifier: Operating System :: OS Independent
Requires-Python: >=3.6
License-File: LICENSE
Requires-Dist: pydataset (==0.2.0)
Requires-Dist: texthero (==1.1.0)
Requires-Dist: dtale (==2.2.0)
Requires-Dist: numpy
Requires-Dist: shap (==0.40.0)
Requires-Dist: matplotlib
Requires-Dist: pandas-profiling (==3.1.0)
Requires-Dist: wordcloud (==1.8.1)
Requires-Dist: seaborn (==0.11.2)
Requires-Dist: pandas
Requires-Dist: datatable (==1.0.0)
Requires-Dist: scikit-learn
Requires-Dist: Jinja2 (==3.1.1)
Requires-Dist: Flask (==2.0.3)
